{
  "devices": {
    "of:000000000a4001d0": {
      "accessDevice": {
        "uplink": "1048576",
        "vlan": "1"
      },
      "basic": {
        "driver": "voltha"
      }
    }
  },
  "apps": {
    "org.opencord.dhcpl2relay": {
      "dhcpl2relay": {
        "useOltUplinkForServerPktInOut": true
      }
    },
    "org.opencord.kafka": {
      "kafka": {
        "bootstrapServers": "172.17.0.1:9092"
      }
    },
    "org.opencord.aaa": {
      "AAA": {
        "radiusIp": "172.17.0.1",
        "radiusServerPort": "1812",
        "radiusSecret": "SECRET",
        "nasIp": "172.17.0.1",
        "radiusConnectionType": "socket"
      }
    },
    "org.opencord.sadis": {
      "sadis": {
        "integration": {
          "cache": {
            "enabled": true,
            "maxsize": 50,
            "ttl": "PT1m"
          }
        },
        "entries": [
          {
            "id": "EC1829000885",
            "uplinkPort": 1048576,
            "hardwareIdentifier": "3c:2c:99:f7:c6:82",
            "ipAddress": "10.64.1.207",
            "nasId": "ATLEDGEVOLT1"
          },
          {
            "id": "ALPHe3d1cf57-1",
            "cTag": 21,
            "sTag": 13,
            "nasPortId": "PON 1/1/3/1:2.1.1",
            "circuitId": "PON 1/1/3/1:2.1.1-CID",
            "remoteId": "ATLEDGEVOLT1-RID",
            "technologyProfileId": 64,
            "upstreamBandwidthProfile": "Default",
            "downstreamBandwidthProfile": "Default"
          },
          {
            "id": "ALPHe3d1cf57-2",
            "cTag": 21,
            "sTag": 13,
            "nasPortId": "PON 1/1/3/1:2.1.1",
            "circuitId": "PON 1/1/3/1:2.1.1-CID",
            "remoteId": "ATLEDGEVOLT1-RID",
            "technologyProfileId": 64,
            "upstreamBandwidthProfile": "Default",
            "downstreamBandwidthProfile": "Default"
          },
          {
            "id": "ALPHe3d1cf57-3",
            "cTag": 21,
            "sTag": 13,
            "nasPortId": "PON 1/1/3/1:2.1.1",
            "circuitId": "PON 1/1/3/1:2.1.1-CID",
            "remoteId": "ATLEDGEVOLT1-RID",
            "technologyProfileId": 64,
            "upstreamBandwidthProfile": "Default",
            "downstreamBandwidthProfile": "Default"
          },
          {
            "id": "ALPHe3d1cf57-4",
            "cTag": 21,
            "sTag": 13,
            "nasPortId": "PON 1/1/3/1:2.1.1",
            "circuitId": "PON 1/1/3/1:2.1.1-CID",
            "remoteId": "ATLEDGEVOLT1-RID",
            "technologyProfileId": 64,
            "upstreamBandwidthProfile": "Default",
            "downstreamBandwidthProfile": "Default"
          },
          {
            "id": "ALPHe3d1cf57-5",
            "cTag": 21,
            "sTag": 13,
            "nasPortId": "PON 1/1/3/1:2.1.1",
            "circuitId": "PON 1/1/3/1:2.1.1-CID",
            "remoteId": "ATLEDGEVOLT1-RID",
            "technologyProfileId": 64,
            "upstreamBandwidthProfile": "Default",
            "downstreamBandwidthProfile": "Default"
          }
        ]
      },
      "bandwidthprofile": {
        "integration": {
          "cache": {
            "enabled": true,
            "maxsize": 40,
            "ttl": "PT1m"
          }
        },
        "entries": [
          {
            "id": "Default",
            "air": 10000000,
            "cbs": 5000,
            "cir": 750000,
            "ebs": 5000,
            "eir": 1000000
          }
        ]
      }
    }
  }
}
